botops-0.2.0.dist-info/METADATA
botops-0.2.0.dist-info/WHEEL
botops-0.2.0.dist-info/licenses/LICENSE.txt
botops/__init__.py
botops/core/__init__.py
botops/core/bot.py
botops/core/client.py
botops/core/engine.py
botops/core/handler.py
botops/telegram/__init__.py
botops/telegram/enums.py
botops/telegram/parametrs.py
botops/telegram/types.py
botops/triggers.py
botops/utils/__init__.py
botops/utils/cleanup.py
botops/utils/loader.py
botops/utils/runner.py
botops/utils/scheduler.py
botops-0.2.0.dist-info/RECORD
